{"inkVersion":21,"root":[[{"->":"REINA_HUB"},["done",{"#f":5,"#n":"g-0"}],null],"done",{"REINA_HUB":[["^NAME: *Jaia*, traveler.","\n","^NAME: What can we do for ya?","\n","ev","str","^Inquire","/str","/ev",{"*":".^.c-0","flg":20},"ev","str","^Leave","/str","/ev",{"*":".^.c-1","flg":20},{"c-0":["^ Are you... treasure hunters?","\n","^Reina: How dare you! We are travelling collectors — antiquarians, if you will!","\n","^Maliya: We're treasure hunters.","\n","^Reina: Collectors. Although... we do have quite a few treasures to trade, if you're interested.","\n",["ev","str","^Inquire Further","/str","/ev",{"*":".^.c-0","flg":20},"ev","str","^Dismiss","/str","/ev",{"*":".^.c-1","flg":20},{"c-0":["^ What do you have?","\n","^Reina: Well, do you have a Luitaere collection?","\n",["ev","str","^Agree","/str","/ev",{"*":".^.c-0","flg":20},"ev","str","^Question","/str","/ev",{"*":".^.c-1","flg":20},"ev","str","^Deny","/str","/ev",{"*":".^.c-2","flg":20},{"c-0":["^ Yes!","\n","^Reina: Fantastic!","\n",{"->":".^.^.g-0"},{"#f":5}],"c-1":["^ ...No?","\n","^Reina: Well here is your opportunity to start one!","\n",{"->":".^.^.g-0"},{"#f":5}],"c-2":["^ No.","\n","^Reina: No problem! Here is a great opportunity to start one!","\n",{"->":".^.^.g-0"},{"#f":5}],"g-0":["<>","^ We recently came into possession of two beautiful, hand-painted, silver-embossed, one-of-a-kind—","\n","^Maliya: It's a pair of Luitaere cards. The five of Dreams and seven of Stones, I believe.","\n","^Caeran: It's the seven of Swords.","\n","^Reina: Yes, right! Uhm... The perfect","\n","ev",{"CNT?":".^.^.c-0"},"/ev",[{"->":".^.b","c":true},{"b":["\n","<>","^ additions","\n",{"->":".^.^.^.14"},null]}],[{"->":".^.b"},{"b":["\n","<>","^ start","\n",{"->":".^.^.^.14"},null]}],"nop","\n","<>","^ to any collection!","\n","^Caeran: And quite a find, as well. Only 55 rings each.","\n","^Maliya: Huh? Collectors would buy them for 90 each—","\n","^Reina: Let's just say 100 rings for the pair! What do you say? ",{"->":"REINA_BATTLE"},"\n",{"#f":5}]}],{"#f":5}],"c-1":["^ Oh, sorry, we're not interested. ","done","\n",{"#f":5}]}],{"#f":5}],"c-1":["^ Just passing by ","done","\n",{"#f":5}]}],{"#f":1}],"REINA_BATTLE":["done",{"#f":1}],"#f":1}],"listDefs":{}}